{
    "seed": 111,
    "problem_class": "SimpleProductionPlanningProblem",
    "problem_params": {
        "n_nodes": 7,
        "density": 0.7,
        "num_groups": 5,
        "num_instruments_per_group": 2,
        "num_machines": 3,
        "num_products": 6
    },
    "circuit_class": "AncillaQAOACircuit",
    "layers": 2,
    "backend": "ibm_marrakesh",
    "logic_qubits": 24,
    "backend_qubits": 156,
    "virtual_qc_metrics": {
        "depth": 64,
        "2q_gates": 312,
        "clifford_gates": 42,
        "non_clifford_gates": 348,
        "t_gates": 0,
        "total_gates": 390,
        "num_active_qubits": 30
    },
    "transpiled_qc_metrics": {
        "depth": 1657,
        "2q_gates": 1821,
        "clifford_gates": 6526,
        "non_clifford_gates": 402,
        "t_gates": 8,
        "total_gates": 6928,
        "num_active_qubits": 32
    },
    "clifford_qc_metrics": {
        "depth": 1657,
        "2q_gates": 1821,
        "clifford_gates": 6928,
        "non_clifford_gates": 0,
        "t_gates": 0,
        "total_gates": 6928,
        "num_active_qubits": 32
    },
    "performance": {
        "only_clifford": true,
        "pruned_noise": false
    },
    "mitigation_technique": "zne",
    "mitigation_params": {
        "factory": "linear",
        "noise_values": [
            1,
            2,
            3
        ]
    },
    "num_estimator_shots": 1024,
    "ideal_energy": null,
    "noisy_energy": null,
    "clifford_ideal_energy": -676.9306640625,
    "clifford_noisy_energy": -303.98046875,
    "clifford_mitigated_energy": -428.6067708333333,
    "error_pct_noisy": 55.09429770462667,
    "error_pct_mitigated": 36.683800337672295,
    "circuit_creation_time": 0.014575712993973866,
    "transpilation_time": 0.5381645309971645,
    "transpilation_clifford_time": 0.6409684770042077,
    "ideal_estimation_time": null,
    "noisy_estimation_time": null,
    "clifford_ideal_estimation_time": 0.8949340549879707,
    "clifford_noisy_estimation_time": 70.7515026970068,
    "clifford_mitigated_estimation_time": 382.92367310400004,
    "zne_factory_plot": "M3_P6_S111_Flinear_out/zne_factory_fit.png"
}